{
  "lastUpdated": "2026-02-15T00:05:00.011Z",
  "generatedBy": "trade-reporter.js v1.0",
  "portfolio": {
    "totalValue": 452.725485,
    "positionValue": 165.2264,
    "cashBalance": 287.499085,
    "trackedPositions": 23,
    "idlePct": "63.5"
  },
  "summary": {
    "totalRealizedPnl": -34.59,
    "totalUnrealizedPnl": 17.59,
    "totalPnl": -17,
    "totalTrades": 59,
    "totalWins": 16,
    "totalLosses": 27,
    "overallWinRate": 34.8,
    "portfolioValue": 452.725485,
    "cashBalance": 287.499085,
    "idlePct": "63.5",
    "activeStrategies": 5,
    "fillStats": {
      "weather": {
        "submitted": 0,
        "filled": 0,
        "partial": 0,
        "unfilled": 0
      },
      "resolution": {
        "submitted": 1,
        "filled": 1,
        "partial": 0,
        "unfilled": 0
      },
      "arb": {
        "submitted": 6,
        "filled": 4,
        "partial": 0,
        "unfilled": 2
      }
    }
  },
  "strategies": {
    "unknown": {
      "status": "ACTIVE",
      "totalTrades": 19,
      "openPositions": 7,
      "closedPositions": 12,
      "wins": 7,
      "losses": 5,
      "winRate": "58.3%",
      "realizedPnl": "$10.32",
      "unrealizedPnl": "$1.46",
      "totalPnl": "$11.78",
      "totalDeployed": "$224.81",
      "currentDeployed": "$4.32",
      "expectancy": "$0.86",
      "profitFactor": "2.07",
      "avgWin": "$2.85",
      "avgLoss": "$-1.92",
      "avgHoldHours": 0,
      "bestTrade": {
        "market": "Gov Shutdown Feb 14",
        "pnl": 18.07,
        "pnlPct": "15.7"
      },
      "worstTrade": {
        "market": "Bad Bunny Halftime Views",
        "pnl": -7.43,
        "pnlPct": "-21.2"
      }
    },
    "arb": {
      "status": "ACTIVE",
      "totalTrades": 10,
      "openPositions": 1,
      "closedPositions": 9,
      "wins": 1,
      "losses": 6,
      "winRate": "11.1%",
      "realizedPnl": "$-1.25",
      "unrealizedPnl": "$9.00",
      "totalPnl": "$7.75",
      "totalDeployed": "$4.38",
      "currentDeployed": "$31.00",
      "expectancy": "$-0.14",
      "profitFactor": "0.05",
      "avgWin": "$0.07",
      "avgLoss": "$-0.22",
      "avgHoldHours": 0,
      "bestTrade": {
        "market": "0xb67faadf0c0d3ce177f996359849f5ea46961f7ef34872e5948ab25eb6a49168",
        "pnl": 0.07,
        "pnlPct": "53.8"
      },
      "worstTrade": {
        "market": "0x27c9827d0da9e1dc91a2c497afe10e8ba852e72e68d7efbe1b7a677542eb31a1",
        "pnl": -0.6,
        "pnlPct": "-33.3"
      }
    },
    "manual": {
      "status": "ACTIVE",
      "totalTrades": 7,
      "openPositions": 5,
      "closedPositions": 2,
      "wins": 0,
      "losses": 2,
      "winRate": "0%",
      "realizedPnl": "$-9.54",
      "unrealizedPnl": "$7.13",
      "totalPnl": "$-2.41",
      "totalDeployed": "$94.60",
      "currentDeployed": "$48.24",
      "expectancy": "$-4.77",
      "profitFactor": "0.00",
      "avgWin": "$0.00",
      "avgLoss": "$-4.77",
      "avgHoldHours": 0,
      "bestTrade": {
        "market": "Bangladesh BNP Election Win",
        "pnl": -1.84,
        "pnlPct": "-2.5"
      },
      "worstTrade": {
        "market": "0xb572085e24472c1039ea8d5a06eaaca249f1d5459b7b09a0d71a89628708924c",
        "pnl": -7.7,
        "pnlPct": "-36.7"
      }
    },
    "weather": {
      "status": "COMPLETED",
      "totalTrades": 19,
      "openPositions": 0,
      "closedPositions": 19,
      "wins": 4,
      "losses": 14,
      "winRate": "21.1%",
      "realizedPnl": "$-34.56",
      "unrealizedPnl": "$0.00",
      "totalPnl": "$-34.56",
      "totalDeployed": "$103.62",
      "currentDeployed": "$0.00",
      "expectancy": "$-1.82",
      "profitFactor": "0.11",
      "avgWin": "$1.06",
      "avgLoss": "$-2.77",
      "avgHoldHours": 0,
      "bestTrade": {
        "market": "London 8°C Feb 13",
        "pnl": 2.06,
        "pnlPct": "50.9"
      },
      "worstTrade": {
        "market": "Buenos Aires ≤27°C 2026-02-13",
        "pnl": -6.6,
        "pnlPct": "-73.3"
      }
    },
    "resolution": {
      "status": "COMPLETED",
      "totalTrades": 4,
      "openPositions": 0,
      "closedPositions": 4,
      "wins": 4,
      "losses": 0,
      "winRate": "100%",
      "realizedPnl": "$0.44",
      "unrealizedPnl": "$0.00",
      "totalPnl": "$0.44",
      "totalDeployed": "$59.50",
      "currentDeployed": "$0.00",
      "expectancy": "$0.11",
      "profitFactor": "∞",
      "avgWin": "$0.11",
      "avgLoss": "$0.00",
      "avgHoldHours": 0,
      "bestTrade": {
        "market": "Will the highest temperature in Ankara be 13°C on February 13?",
        "pnl": 0.16,
        "pnlPct": "1.1"
      },
      "worstTrade": {
        "market": "Will the highest temperature in Toronto be 3°C or higher on February 13?",
        "pnl": 0.07,
        "pnlPct": "0.5"
      }
    }
  }
}